LICENSE
MANIFEST.in
README.md
setup.py
rigur/__init__.py
rigur/__main__.py
rigur.egg-info/PKG-INFO
rigur.egg-info/SOURCES.txt
rigur.egg-info/dependency_links.txt
rigur.egg-info/entry_points.txt
rigur.egg-info/requires.txt
rigur.egg-info/top_level.txt
rigur/backend/DraggablePoint.py
rigur/gui/rigur.py