Metadata-Version: 2.1
Name: rigur
Version: 0.0.3
Summary: Rip data from images of figures
Home-page: https://github.com/dfujim/rigur
Author: Derek Fujimoto
Author-email: fujimoto@phas.ubc.ca
License: UNKNOWN
Platform: UNKNOWN
Classifier: Programming Language :: Python :: 3
Classifier: Programming Language :: Python :: 3.6
Classifier: Programming Language :: Python :: 3.7
Classifier: License :: OSI Approved :: GNU Lesser General Public License v3 (LGPLv3)
Classifier: Operating System :: POSIX :: Linux
